LICENSE
MANIFEST.in
README.rst
setup.py
jsl/__init__.py
jsl/document.py
jsl/exceptions.py
jsl/registry.py
jsl/resolutionscope.py
jsl/roles.py
jsl.egg-info/PKG-INFO
jsl.egg-info/SOURCES.txt
jsl.egg-info/dependency_links.txt
jsl.egg-info/top_level.txt
jsl/_compat/__init__.py
jsl/_compat/ordereddict.py
jsl/_compat/prepareable.py
jsl/fields/__init__.py
jsl/fields/base.py
jsl/fields/compound.py
jsl/fields/primitive.py
jsl/fields/util.py